<?xml version="1.0" encoding="utf-8" standalone="yes"?>
<SENSEPOOL SPID="come into view, notice or being" FID="P16400" NAME="P16400">
  <SENSE>
    <SENSEID>surface.e.o.v.1</SENSEID>
    <SENSEID>appear.e.o.v.2</SENSEID>
    <SENSEID>break.e.o.v.7</SENSEID>
    <SENSEID>come.e.o.v.5</SENSEID>
    <SENSEID>emerge.e.o.v.1</SENSEID>
    <SENSEID>present.e.o.v.9</SENSEID>
  </SENSE>
  <SUBTO>
    <SUBTAG>Change</SUBTAG>
  </SUBTO>
  <COMMENTARY>Description: come into view, notice or being
Commentary: Break this class apart, with some pools to CH of Integr and some to Incidental or CH of Perceptibility</COMMENTARY>
</SENSEPOOL>
