<?xml version="1.0" encoding="utf-8" standalone="yes"?>
<SENSEPOOL FID="P2243" SPID="Depletion - the state of having a reduced amount of a resource" NAME="P2243">
  <SENSE>
    <SENSEID>depletion.e.o.n.2</SENSEID>
    <SENSEID>depletion.e.y.n.2</SENSEID>
  </SENSE>
  <SUBTO>
    <SUBTAG>P2373</SUBTAG>
    <SUBTAG>StateAsObject</SUBTAG>
  </SUBTO>
  <RELATION>
    <RELATIONTAG>P2242</RELATIONTAG>
  </RELATION>
  <COMMENTARY>the state of having a reduced amount of a resource</COMMENTARY>
</SENSEPOOL>
