<?xml version="1.0" encoding="utf-8" standalone="yes"?>
<SENSEPOOL FID="P2371" SPID="Link - a computer instruction that connects distributed data" NAME="P2371">
  <SENSE>
    <SENSEID>link.e.o.n.7</SENSEID>
    <SENSEID>link.e.y.n.10</SENSEID>
  </SENSE>
  <SUBTO>
    <SUBTAG>GeneralizedLanguageObject</SUBTAG>
  </SUBTO>
  <RELATION>
    <RELATIONTAG>P1711</RELATIONTAG>
  </RELATION>
  <COMMENTARY>a computer instruction that connects data that are otherwise disconnected from each other.</COMMENTARY>
</SENSEPOOL>
