<?xml version="1.0" encoding="utf-8" standalone="yes"?>
<SENSEPOOL FID="P2486" SPID="Realism - philosophical doctrine" NAME="P2486">
  <SENSE>
    <SENSEID>realism.e.o.n.5</SENSEID>
    <SENSEID>realism.e.y.n.6</SENSEID>
    <SENSEID>realism.e.y.n.7</SENSEID>
  </SENSE>
  <SUBTO>
    <SUBTAG>P1460</SUBTAG>
    <SUBTAG>NonImaginaryThoughtObject</SUBTAG>
  </SUBTO>
  <RELATION></RELATION>
  <COMMENTARY>a philosophical doctrine which asserts the existence of physical objects independently from the mind.</COMMENTARY>
</SENSEPOOL>
