<?xml version="1.0" encoding="utf-8" standalone="yes"?>
<SENSEPOOL FID="P2495" SPID="Recognition - public credit, acknowledgment for some merit" NAME="P2495">
  <SENSE>
    <SENSEID>recognition.e.o.n.1</SENSEID>
    <SENSEID>recognition.e.y.n.2</SENSEID>
    <SENSEID>recognition.e.y.n.5</SENSEID>
    <SENSEID>recognition.e.y.n.8</SENSEID>
    <SENSEID>acknowledgment.e.o.n.1</SENSEID>
    <SENSEID>acknowledgment.e.y.n.3</SENSEID>
    <SENSEID>appreciation.e.y.n.2</SENSEID>
    <SENSEID>approval.e.y.n.1</SENSEID>
    <SENSEID>credit.e.o.n.3</SENSEID>
    <SENSEID>credit.e.y.n.4</SENSEID>
    <SENSEID>credit.e.y.n.7</SENSEID>
    <SENSEID>acclaim.e.o.n.2</SENSEID>
  </SENSE>
  <SUBTO>
    <SUBTAG>SocialAbstraction</SUBTAG>
  </SUBTO>
  <RELATION>
    <RELATIONTAG>P2478</RELATIONTAG>
  </RELATION>
  <COMMENTARY>being widely, or publicly, given credit for some merit, being acknowledged for merit</COMMENTARY>
</SENSEPOOL>
