<?xml version="1.0" encoding="utf-8" standalone="yes"?>
<SENSEPOOL FID="P2682" SPID="Concentration - ongoing emphasis, focus, prioritization of something" NAME="P2682">
  <SENSE>
    <SENSEID>concentration.e.o.n.5</SENSEID>
    <SENSEID>concentration.e.y.n.7</SENSEID>
    <SENSEID>emphasis.e.o.n.1</SENSEID>
    <SENSEID>emphasis.e.y.n.4</SENSEID>
    <SENSEID>priority.e.o.n.1</SENSEID>
    <SENSEID>priority.e.y.n.2</SENSEID>
    <SENSEID>accent.e.o.n.5</SENSEID>
    <SENSEID>accent.e.y.n.6</SENSEID>
    <SENSEID>attention.e.o.n.3</SENSEID>
    <SENSEID>attention.e.y.n.11</SENSEID>
    <SENSEID>direction.e.o.n.6</SENSEID>
    <SENSEID>direction.e.y.n.5</SENSEID>
  </SENSE>
  <SUBTO>
    <SUBTAG>MentalState</SUBTAG>
    <SUBTAG>StateAsObject</SUBTAG>
    <SUBTAG>ThoughtProcess</SUBTAG>
  </SUBTO>
  <RELATION></RELATION>
  <COMMENTARY>implies ongoing allocation of interest and resources to something</COMMENTARY>
</SENSEPOOL>
