<?xml version="1.0" encoding="utf-8" standalone="yes"?>
<SENSEPOOL FID="P2706" SPID="Defense - protective action or move" NAME="P2706">
  <SENSE>
    <SENSEID>defense.e.o.n.2</SENSEID>
    <SENSEID>defense.e.y.n.1</SENSEID>
    <SENSEID>defense.e.y.n.2</SENSEID>
    <SENSEID>defense.e.y.n.6</SENSEID>
    <SENSEID>defense.e.y.n.14</SENSEID>
    <SENSEID>protection.e.o.n.2</SENSEID>
    <SENSEID>protection.e.y.n.1</SENSEID>
    <SENSEID>security.e.o.n.5</SENSEID>
    <SENSEID>security.e.y.n.1</SENSEID>
    <SENSEID>security.e.y.n.9</SENSEID>
    <SENSEID>ward.e.o.n.8</SENSEID>
  </SENSE>
  <SUBTO>
    <SUBTAG>EventAsObject</SUBTAG>
  </SUBTO>
  <RELATION>
    <RELATIONTAG>P1323</RELATIONTAG>
  </RELATION>
  <COMMENTARY>action that serves a protective action, often of a military nature.</COMMENTARY>
</SENSEPOOL>
