<?xml version="1.0" encoding="utf-8" standalone="yes"?>
<SENSEPOOL FID="P2877" SPID="Relief - sequential replacement, backup" NAME="P2877">
  <SENSE>
    <SENSEID>relief.e.o.n.3</SENSEID>
    <SENSEID>relief.e.y.n.12</SENSEID>
    <SENSEID>replacement.e.y.n.5</SENSEID>
    <SENSEID>substitute.e.y.n.3</SENSEID>
  </SENSE>
  <SUBTO>
    <SUBTAG>P2885</SUBTAG>
    <SUBTAG>Human</SUBTAG>
    <SUBTAG>NonProfessionRole</SUBTAG>
  </SUBTO>
  <RELATION></RELATION>
  <COMMENTARY>someone or something that replaces another in sequence, as a backup or tag-team</COMMENTARY>
</SENSEPOOL>
