<?xml version="1.0" encoding="utf-8" standalone="yes"?>
<SENSEPOOL FID="P2961" SPID="Cell - small enclosed uniform component" NAME="P2961">
  <SENSE>
    <SENSEID>cell.e.o.n.3</SENSEID>
    <SENSEID>cell.e.y.n.6</SENSEID>
  </SENSE>
  <SUBTO>
    <SUBTAG>P2029</SUBTAG>
    <SUBTAG>Artifact</SUBTAG>
    <SUBTAG>PartOf*Artifact</SUBTAG>
    <SUBTAG>ShapeAndStructureAbstraction</SUBTAG>
  </SUBTO>
  <RELATION>
    <RELATIONTAG>P1209</RELATIONTAG>
  </RELATION>
  <COMMENTARY>a small uniform component or compartment, one of many that make up a larger structure.</COMMENTARY>
</SENSEPOOL>
