<?xml version="1.0" encoding="utf-8" standalone="yes"?>
<SENSEPOOL SPID="Injury - the violation of one's rights for which there is legal redress" NAME="P3163" FID="P3163">
  <SENSE>
    <SENSEID>injury.e.o.n.3</SENSEID>
    <SENSEID>tort.e.o.n.1</SENSEID>
  </SENSE>
  <SUBTO>
    <SUBTAG>EventAsObject</SUBTAG>
    <SUBTAG>SocialAbstraction</SUBTAG>
  </SUBTO>
  <RELATION>
    <RELATIONTAG>P2669</RELATIONTAG>
  </RELATION>
  <COMMENTARY>the violation of one's rights and which has legal recourse</COMMENTARY>
</SENSEPOOL>
